pytest_boto_mock/__init__.py
pytest_boto_mock/_version.py
pytest_boto_mock/plugin.py
pytest_boto_mock/py.typed
pytest_boto_mock-0.4.0.dist-info/licenses/LICENSE
pytest_boto_mock-0.4.0.dist-info/METADATA
pytest_boto_mock-0.4.0.dist-info/WHEEL
pytest_boto_mock-0.4.0.dist-info/entry_points.txt
pytest_boto_mock-0.4.0.dist-info/top_level.txt
pytest_boto_mock-0.4.0.dist-info/RECORD
