Metadata-Version: 2.4
Name: pytest-boto-mock
Version: 0.4.0
Summary: Thin-wrapper around the mock package for easier use with pytest
Author-email: H1Gdev <h1g.z.ouroboros+github@gmail.com>
License:                                  Apache License
Project-URL: Homepage, https://github.com/H1Gdev/pytest-boto-mock/
Project-URL: Source, https://github.com/H1Gdev/pytest-boto-mock/
Project-URL: Tracker, https://github.com/H1Gdev/pytest-boto-mock/issues
Keywords: pytest,botocore,pytest-mock
Classifier: Development Status :: 5 - Production/Stable
Classifier: Framework :: Pytest
Classifier: Intended Audience :: Developers
Classifier: License :: OSI Approved :: Apache Software License
Classifier: Operating System :: OS Independent
Classifier: Programming Language :: Python :: 3
Classifier: Programming Language :: Python :: 3 :: Only
Classifier: Programming Language :: Python :: 3.9
Classifier: Programming Language :: Python :: 3.10
Classifier: Programming Language :: Python :: 3.11
Classifier: Programming Language :: Python :: 3.12
Classifier: Programming Language :: Python :: 3.13
Classifier: Topic :: Software Development :: Testing
Requires-Python: >=3.9
License-File: LICENSE
Requires-Dist: botocore
Requires-Dist: pytest>=8.2.0
Requires-Dist: pytest-mock
Provides-Extra: dev
Requires-Dist: boto3; extra == "dev"
Requires-Dist: tox; extra == "dev"
Dynamic: license-file
